failure_analysis/__init__.py
failure_analysis/drain3.ini
failure_analysis/failure_analysis.py
failure_analysis/py.typed
failures_analysis-2.1.0.dist-info/entry_points.txt
failures_analysis-2.1.0.dist-info/LICENSE.md
failures_analysis-2.1.0.dist-info/WHEEL
failures_analysis-2.1.0.dist-info/METADATA
failures_analysis-2.1.0.dist-info/RECORD
