Metadata-Version: 2.1
Name: failures-analysis
Version: 2.1.0
Summary:  failures-analysis package provides fast and reliable way to find and group similar failures in test automation.
Home-page: https://github.com/F-Secure/failures-analysis
License: Apache-2.0
Author: Tatu Aalto
Requires-Python: >=3.8,<4.0
Classifier: Development Status :: 3 - Alpha
Classifier: License :: OSI Approved :: Apache Software License
Classifier: Operating System :: OS Independent
Classifier: Programming Language :: Python :: 3
Classifier: Programming Language :: Python :: 3.8
Classifier: Programming Language :: Python :: 3.9
Classifier: Programming Language :: Python :: 3.10
Classifier: Programming Language :: Python :: 3.11
Classifier: Programming Language :: Python :: 3
Classifier: Programming Language :: Python :: 3.10
Classifier: Programming Language :: Python :: 3.8
Classifier: Programming Language :: Python :: 3.9
Classifier: Topic :: Software Development :: Testing
Requires-Dist: drain3 (>=0.9.11,<0.10.0)
Requires-Dist: lxml (>=4.9.1,<5.0.0)
Requires-Dist: numpy (>=1.23.5,<2.0.0)
Requires-Dist: pandas (>=1.5.1,<2.0.0)
Requires-Dist: scikit-learn (>=1.1.3,<2.0.0)
Project-URL: Change log, https://github.com/F-Secure/failures-analysis/blob/main/CHANGELOG.md
